odoo/addons/l10n_es_facturae_face/README.rst
odoo/addons/l10n_es_facturae_face/__init__.py
odoo/addons/l10n_es_facturae_face/__manifest__.py
odoo/addons/l10n_es_facturae_face/components/__init__.py
odoo/addons/l10n_es_facturae_face/components/account_move_l10n_es_facturae_face_listener.py
odoo/addons/l10n_es_facturae_face/components/account_move_l10n_es_facturae_listener.py
odoo/addons/l10n_es_facturae_face/components/edi_input_process_l10n_es_facturae_l10n_es_facturae_face_update.py
odoo/addons/l10n_es_facturae_face/components/edi_output_l10n_es_facturae.py
odoo/addons/l10n_es_facturae_face/components/edi_send_l10n_es_facturae_face.py
odoo/addons/l10n_es_facturae_face/components/edi_send_l10n_es_facturae_face_cancel.py
odoo/addons/l10n_es_facturae_face/components/edi_webservice_receive_face_l10n_es_facturae_face_update.py
odoo/addons/l10n_es_facturae_face/components/webservice_face.py
odoo/addons/l10n_es_facturae_face/data/cron_data.xml
odoo/addons/l10n_es_facturae_face/data/edi.xml
odoo/addons/l10n_es_facturae_face/data/face_data.xml
odoo/addons/l10n_es_facturae_face/i18n/es.po
odoo/addons/l10n_es_facturae_face/i18n/l10n_es_facturae_face.pot
odoo/addons/l10n_es_facturae_face/migrations/13.0.1.0.1/post-migration.py
odoo/addons/l10n_es_facturae_face/migrations/13.0.2.0.0/pre-migration.py
odoo/addons/l10n_es_facturae_face/migrations/13.0.3.0.0/post-migration.py
odoo/addons/l10n_es_facturae_face/migrations/13.0.3.0.0/pre-migration.py
odoo/addons/l10n_es_facturae_face/models/__init__.py
odoo/addons/l10n_es_facturae_face/models/account_move.py
odoo/addons/l10n_es_facturae_face/models/edi_exchange_record.py
odoo/addons/l10n_es_facturae_face/models/res_company.py
odoo/addons/l10n_es_facturae_face/models/res_partner.py
odoo/addons/l10n_es_facturae_face/models/wsse_signature.py
odoo/addons/l10n_es_facturae_face/readme/CONFIGURE.rst
odoo/addons/l10n_es_facturae_face/readme/CONTRIBUTORS.rst
odoo/addons/l10n_es_facturae_face/readme/DESCRIPTION.rst
odoo13_addon_l10n_es_facturae_face-13.0.3.1.1.dist-info/METADATA
odoo13_addon_l10n_es_facturae_face-13.0.3.1.1.dist-info/WHEEL
odoo13_addon_l10n_es_facturae_face-13.0.3.1.1.dist-info/top_level.txt
odoo13_addon_l10n_es_facturae_face-13.0.3.1.1.dist-info/RECORD
