Metadata-Version: 2.1
Name: odoo13-addon-l10n-es-facturae-face
Version: 13.0.3.1.1
Summary: Envío de Factura-e a FACe
Home-page: https://github.com/OCA/l10n-spain
Author: Creu Blanca, Odoo Community Association (OCA)
Author-email: support@odoo-community.org
License: AGPL-3
Platform: UNKNOWN
Classifier: Programming Language :: Python
Classifier: Framework :: Odoo
Classifier: Framework :: Odoo :: 13.0
Classifier: License :: OSI Approved :: GNU Affero General Public License v3
Requires-Python: >=3.5
Requires-Dist: odoo13-addon-edi-account
Requires-Dist: odoo13-addon-l10n-es-facturae
Requires-Dist: odoo <13.1dev,>=13.0a
Requires-Dist: pyOpenSSL
Requires-Dist: xmlsec
Requires-Dist: zeep
